[{"name":"Calculate","label":"Calculate","description":"[[Calculate.description]]","nodeLabel":"[[Calculate.node_label]]","mainClass":"com.automationanywhere.botcommand.samples.commands.basic.CalculateCommand","icon":"pkg.svg","returnType":"NUMBER","returnSubtype":"UNDEFINED","returnLabel":"","returnRequired":true,"returnDescription":"[[Calculate.return_description]]","attributes":[{"name":"i_tabela","label":"[[Calculate.table.label]]","description":"[[Calculate.table.description]]","type":"TABLE","rules":[{"name":"NOT_EMPTY"}]},{"name":"i_colunasCalc","label":"[[Calculate.cols.label]]","description":"[[Calculate.cols.description]]","type":"TEXT","rules":[{"name":"NOT_EMPTY"}]},{"name":"i_code","label":"[[Calculate.code.label]]","description":"[[Calculate.code.description]]","type":"CODE","rules":[{"name":"NOT_EMPTY"},{"name":"CODE_TYPE","value":"text/javascript"}]}]},{"name":"ColumnToList","label":"ColumnToList","description":"[[ColumnToList.description]]","nodeLabel":"[[ColumnToList.node_label]]","mainClass":"com.automationanywhere.botcommand.samples.commands.basic.ColumnToListCommand","icon":"pkg.svg","returnType":"LIST","returnSubtype":"UNDEFINED","returnLabel":"","returnRequired":true,"returnDescription":"[[ColumnToList.return_description]]","attributes":[{"name":"Tabela","label":"[[ColumnToList.table.label]]","description":"[[ColumnToList.table.description]]","type":"TABLE","rules":[{"name":"NOT_EMPTY"}]},{"name":"getby","label":"[[ColumnToList.getby.label]]","description":"[[ColumnToList.getby.description]]","type":"SELECT","defaultValue":{"string":"name","type":"STRING"},"rules":[{"name":"NOT_EMPTY"}],"options":[{"label":"ByName","value":"name","attributes":[{"name":"byname","label":"[[ColumnToList.byname.label]]","description":"[[ColumnToList.byname.description]]","type":"TEXT","rules":[{"name":"NOT_EMPTY"}]}]},{"label":"ByIndex","value":"index","attributes":[{"name":"bynindex","label":"[[ColumnToList.byindex.label]]","description":"[[ColumnToList.byindex.description]]","type":"NUMBER","rules":[{"name":"NOT_EMPTY"}]}]}]}]},{"name":"DeleteColumns","label":"DeleteColumns","description":"[[DeleteColumns.description]]","nodeLabel":"[[DeleteColumns.node_label]]","mainClass":"com.automationanywhere.botcommand.samples.commands.basic.DeleteColumnsCommand","icon":"pkg.svg","returnType":"TABLE","returnSubtype":"UNDEFINED","returnLabel":"","returnRequired":true,"returnDescription":"[[DeleteColumns.return_description]]","attributes":[{"name":"Tabela","label":"[[DeleteColumns.table.label]]","description":"[[DeleteColumns.table.description]]","type":"TABLE","rules":[{"name":"NOT_EMPTY"}]},{"name":"colunas","label":"[[DeleteColumns.cols.label]]","description":"[[DeleteColumns.cols.description]]","type":"TEXT","rules":[{"name":"NOT_EMPTY"}]}]},{"name":"FilterRegister","label":"FilterRegister","description":"[[FilterRegister.description]]","nodeLabel":"[[FilterRegister.node_label]]","mainClass":"com.automationanywhere.botcommand.samples.commands.basic.FilterRegisterCommand","icon":"pkg.svg","returnType":"TABLE","returnSubtype":"UNDEFINED","returnLabel":"","returnRequired":true,"returnDescription":"[[FilterRegister.return_description]]","attributes":[{"name":"Tabela","label":"[[FilterRegister.table.label]]","description":"[[FilterRegister.table.description]]","type":"TABLE","rules":[{"name":"NOT_EMPTY"}]},{"name":"i_colunas","label":"[[FilterRegister.cols.label]]","description":"[[FilterRegister.cols.description]]","type":"TEXT"},{"name":"code","label":"[[FilterRegister.code.label]]","description":"[[FilterRegister.code.description]]","type":"CODE","rules":[{"name":"NOT_EMPTY"},{"name":"CODE_TYPE","value":"text/javascript"}]}]},{"name":"ReorderColumns","label":"ReorderColumns","description":"[[ReorderColumns.description]]","nodeLabel":"[[ReorderColumns.node_label]]","mainClass":"com.automationanywhere.botcommand.samples.commands.basic.ReorderColumnsCommand","icon":"pkg.svg","returnType":"TABLE","returnSubtype":"UNDEFINED","returnLabel":"","returnRequired":true,"returnDescription":"[[ReorderColumns.return_description]]","attributes":[{"name":"Tabela","label":"[[ReorderColumns.table.label]]","description":"[[ReorderColumns.table.description]]","type":"TABLE","rules":[{"name":"NOT_EMPTY"}]},{"name":"colunas","label":"[[ReorderColumns.cols.label]]","description":"[[ReorderColumns.cols.description]]","type":"TEXT","rules":[{"name":"NOT_EMPTY"}]}]},{"name":"RowToHeaders","label":"RowToHeaders","description":"[[RowToHeaders.description]]","nodeLabel":"[[RowToHeaders.node_label]]","mainClass":"com.automationanywhere.botcommand.samples.commands.basic.RowToHeadersCommand","icon":"pkg.svg","returnType":"TABLE","returnSubtype":"UNDEFINED","returnLabel":"","returnRequired":true,"returnDescription":"[[RowToHeaders.return_description]]","attributes":[{"name":"Tabela","label":"[[RowToHeaders.table.label]]","description":"[[RowToHeaders.table.description]]","type":"TABLE","rules":[{"name":"NOT_EMPTY"}]},{"name":"rowIdx","label":"[[RowToHeaders.rowIdx.label]]","description":"[[RowToHeaders.rowIdx.description]]","type":"NUMBER","rules":[{"name":"NOT_EMPTY"},{"name":"GREATER_THAN_EQUALS","value":"0"}]},{"name":"deleteRow","label":"[[RowToHeaders.deleteRow.label]]","description":"[[RowToHeaders.deleteRow.description]]","type":"CHECKBOX","defaultValue":{"boolean":false,"type":"BOOLEAN"},"rules":[{"name":"NOT_EMPTY"}]}]},{"name":"RowToList","label":"RowToList","description":"[[RowToList.description]]","nodeLabel":"[[RowToList.node_label]]","mainClass":"com.automationanywhere.botcommand.samples.commands.basic.RowToListCommand","icon":"pkg.svg","returnType":"LIST","returnSubtype":"STRING","returnLabel":"","returnRequired":true,"returnDescription":"[[RowToList.return_description]]","attributes":[{"name":"type","label":"[[RowToList.type.label]]","description":"[[RowToList.type.description]]","type":"SELECT","defaultValue":{"string":"record","type":"STRING"},"rules":[{"name":"NOT_EMPTY"}],"options":[{"label":"Record","value":"record","attributes":[{"name":"record","label":"[[RowToList.record.label]]","description":"[[RowToList.record.description]]","type":"RECORD","rules":[{"name":"NOT_EMPTY"}]}]},{"label":"Table","value":"table","attributes":[{"name":"Tabela","label":"[[RowToList.table.label]]","description":"[[RowToList.table.description]]","type":"TABLE","rules":[{"name":"NOT_EMPTY"}]},{"name":"row","label":"[[RowToList.row.label]]","description":"[[RowToList.row.description]]","type":"NUMBER","rules":[{"name":"NOT_EMPTY"},{"name":"GREATER_THAN_EQUALS","value":"0"}]}]}]}]},{"name":"SetColumnName","label":"SetColumnName","description":"[[SetColumnName.description]]","nodeLabel":"[[SetColumnName.node_label]]","mainClass":"com.automationanywhere.botcommand.samples.commands.basic.SetColumnNameCommand","icon":"pkg.svg","returnType":"TABLE","returnSubtype":"UNDEFINED","returnLabel":"","returnRequired":true,"returnDescription":"[[SetColumnName.return_description]]","attributes":[{"name":"Tabela","label":"[[SetColumnName.table.label]]","description":"[[SetColumnName.table.description]]","type":"TABLE","rules":[{"name":"NOT_EMPTY"}]},{"name":"TypeIndex","label":"[[SetColumnName.col.label]]","description":"[[SetColumnName.col.description]]","type":"SELECT","defaultValue":{"string":"name","type":"STRING"},"rules":[{"name":"NOT_EMPTY"}],"options":[{"label":"ByName","value":"name","attributes":[{"name":"ColumnName","label":"[[SetColumnName.colname.label]]","description":"[[SetColumnName.colname.description]]","type":"TEXT","rules":[{"name":"NOT_EMPTY"}]}]},{"label":"ByIndex","value":"index","attributes":[{"name":"ColumnIndex","label":"[[SetColumnName.colidx.label]]","description":"[[SetColumnName.colidx.description]]","type":"NUMBER","rules":[{"name":"NOT_EMPTY"}]}]}]},{"name":"NewColumnName","label":"[[SetColumnName.colnew.label]]","description":"[[SetColumnName.colnew.label]]","type":"TEXT","rules":[{"name":"NOT_EMPTY"}]}]},{"name":"TableColumnForm","label":"TableColumnForm","description":"[[TableColumnForm.description]]","nodeLabel":"[[TableColumnForm.node_label]]","mainClass":"com.automationanywhere.botcommand.samples.commands.basic.TableColumnFormCommand","icon":"pkg.svg","returnType":"TABLE","returnSubtype":"UNDEFINED","returnLabel":"","returnRequired":true,"returnDescription":"[[TableColumnForm.return_description]]","attributes":[{"name":"Tabela","label":"[[TableColumnForm.table.label]]","description":"[[TableColumnForm.table.description]]","type":"TABLE","rules":[{"name":"NOT_EMPTY"}]},{"name":"i_colunas","label":"[[TableColumnForm.cols.label]]","description":"[[TableColumnForm.cols.description]]","type":"TEXT","rules":[{"name":"NOT_EMPTY"}]},{"name":"typeNewCol","label":"[[TableColumnForm.colnewtype.label]]","description":"[[TableColumnForm.colnewtype.description]]","type":"SELECT","defaultValue":{"string":"new","type":"STRING"},"rules":[{"name":"NOT_EMPTY"}],"options":[{"label":"NewColumn","value":"new"},{"label":"UpdateColumn","value":"update"}]},{"name":"colType","label":"[[TableColumnForm.coltype.label]]","description":"[[TableColumnForm.coltype.description]]","type":"SELECT","defaultValue":{"string":"name","type":"STRING"},"rules":[{"name":"NOT_EMPTY"}],"options":[{"label":"ByName","value":"name","attributes":[{"name":"i_columnName","label":"[[TableColumnForm.col.label]]","description":"[[TableColumnForm.col.description]]","type":"TEXT","rules":[{"name":"NOT_EMPTY"}]}]},{"label":"ByIndex","value":"index","attributes":[{"name":"i_idx","label":"[[TableColumnForm.colidx.label]","description":"[[TableColumnForm.colidx.description]","type":"NUMBER","rules":[{"name":"NOT_EMPTY"},{"name":"GREATER_THAN_EQUALS","value":"0"}]},{"name":"i_columnNameByIndex","label":"[[TableColumnForm.colname.label]]","description":"[[TableColumnForm.colname.description]]","type":"TEXT","rules":[{"name":"NOT_EMPTY"}]}]}]},{"name":"code","label":"[[TableColumnForm.code.label]]","description":"[[TableColumnForm.code.description]]","type":"CODE","rules":[{"name":"NOT_EMPTY"},{"name":"CODE_TYPE","value":"text/javascript"}]}]},{"name":"TableQuery","label":"TableQuery","description":"[[TableQuery.description]]","nodeLabel":"[[TableQuery.node_label]]","mainClass":"com.automationanywhere.botcommand.samples.commands.basic.TableQueryCommand","icon":"pkg.svg","returnType":"LIST","returnSubtype":"STRING","returnLabel":"","returnRequired":true,"returnDescription":"[[TableQuery.return_description]]","attributes":[{"name":"Tabela","label":"[[TableQuery.table.label]]","description":"[[TableQuery.table.description]]","type":"TABLE","rules":[{"name":"NOT_EMPTY"}]},{"name":"registros","label":"[[TableQuery.reg.label]]","description":"[[TableQuery.reg.description]]","type":"NUMBER","rules":[{"name":"NOT_EMPTY"}]},{"name":"i_colunas","label":"[[TableQuery.col.label]]","description":"[[TableQuery.col.description]]","type":"TEXT"},{"name":"isMysql","label":"[[TableQuery.mysql.label]]","description":"[[TableQuery.mysql.description]]","type":"CHECKBOX","defaultValue":{"boolean":false,"type":"BOOLEAN"},"rules":[{"name":"NOT_EMPTY"}]},{"name":"i_colunasUSD","label":"[[TableQuery.usd.label]]","description":"[[TableQuery.usd.description]]","type":"TEXT"},{"name":"i_colunasBRLUSD","label":"[[TableQuery.usdbrl.label]]","description":"[[TableQuery.usdbrl.description]]","type":"TEXT"}]},{"name":"TableToXLS","label":"TableToXLS","description":"[[TableToXLS.description]]","nodeLabel":"[[TableToXLS.node_label]]","mainClass":"com.automationanywhere.botcommand.samples.commands.basic.TableToXLSCommand","icon":"pkg.svg","returnType":"STRING","returnSubtype":"UNDEFINED","returnLabel":"","returnRequired":false,"returnDescription":"[[TableToXLS.return_description]]","attributes":[{"name":"tabela","label":"[[TableToXLS.table.label]]","description":"[[TableToXLS.table.description]]","type":"TABLE","rules":[{"name":"NOT_EMPTY"}]},{"name":"outputFile","label":"[[TableToXLS.output.label]]","description":"[[TableToXLS.output.description]]","type":"FILE","rules":[{"name":"NOT_EMPTY"},{"name":"FILE_EXTENSION","value":".xls"}]}]},{"name":"TableToXLSX","label":"TableToXLSX","description":"[[TableToXLSX.description]]","nodeLabel":"[[TableToXLSX.node_label]]","mainClass":"com.automationanywhere.botcommand.samples.commands.basic.TableToXLSXCommand","icon":"pkg.svg","returnType":"STRING","returnSubtype":"UNDEFINED","returnLabel":"","returnRequired":false,"returnDescription":"[[TableToXLSX.return_description]]","attributes":[{"name":"tabela","label":"[[TableToXLSX.table.label]]","description":"[[TableToXLSX.table.description]]","type":"TABLE","rules":[{"name":"NOT_EMPTY"}]},{"name":"outputFile","label":"[[TableToXLSX.output.label]]","description":"[[TableToXLSX.output.description]]","type":"FILE","rules":[{"name":"NOT_EMPTY"},{"name":"FILE_EXTENSION","value":".xlsx"}]}]},{"name":"TrimHeaders","label":"TrimHeaders","description":"[[TrimHeaders.description]]","nodeLabel":"[[TrimHeaders.node_label]]","mainClass":"com.automationanywhere.botcommand.samples.commands.basic.TrimHeadersCommand","icon":"pkg.svg","returnType":"TABLE","returnSubtype":"UNDEFINED","returnLabel":"","returnRequired":true,"returnDescription":"[[TrimHeaders.return_description]]","attributes":[{"name":"Tabela","label":"[[TrimHeaders.table.label]]","description":"[[TrimHeaders.table.description]]","type":"TABLE","rules":[{"name":"NOT_EMPTY"}]}]},{"name":"XlsxToTable","label":"XlsxToTable","description":"[[XlsxToTable.description]]","nodeLabel":"[[XlsxToTable.node_label]]","mainClass":"com.automationanywhere.botcommand.samples.commands.basic.XlsxToTableCommand","icon":"pkg.svg","returnType":"TABLE","returnSubtype":"UNDEFINED","returnLabel":"","returnRequired":true,"returnDescription":"[[XlsxToTable.return_description]]","attributes":[{"name":"file","label":"[[XlsxToTable.file.label]]","description":"[[XlsxToTable.file.description]]","type":"FILE","rules":[{"name":"NOT_EMPTY"},{"name":"FILE_EXTENSION","value":".xlsx"}]},{"name":"getSheetBy","label":"[[XlsxToTable.sheetby.label]]","description":"[[XlsxToTable.sheetby.description]]","type":"SELECT","defaultValue":{"string":"name","type":"STRING"},"rules":[{"name":"NOT_EMPTY"}],"options":[{"label":"ByName","value":"name","attributes":[{"name":"sheetName","label":"[[XlsxToTable.sheetname.label]]","description":"[[XlsxToTable.sheetname.description]]","type":"TEXT","rules":[{"name":"NOT_EMPTY"}]}]},{"label":"ByIndex","value":"index","attributes":[{"name":"sheetIndex","label":"[[XlsxToTable.sheetidx.label]]","description":"[[XlsxToTable.sheetidx.description]]","type":"NUMBER","rules":[{"name":"NOT_EMPTY"},{"name":"GREATER_THAN_EQUALS","value":"0"}]}]}]},{"name":"Columns","label":"[[XlsxToTable.cols.label]]","description":"[[XlsxToTable.cols.description]]","type":"TEXT","rules":[{"name":"NOT_EMPTY"}]},{"name":"hasHeaders","label":"[[XlsxToTable.header.label]]","description":"[[XlsxToTable.header.description]]","type":"CHECKBOX","defaultValue":{"boolean":false,"type":"BOOLEAN"},"rules":[{"name":"NOT_EMPTY"}]},{"name":"RowStartCheck","label":"[[XlsxToTable.startcheck.label]]","description":"[[XlsxToTable.startcheck.description]]","type":"CHECKBOX","defaultValue":{"boolean":false,"type":"BOOLEAN"},"rules":[{"name":"NOT_EMPTY"}],"attributes":[{"name":"RowStart","label":"[[XlsxToTable.startrow.label]]","description":"[[XlsxToTable.startrow.description]]","type":"NUMBER","rules":[{"name":"NOT_EMPTY"},{"name":"GREATER_THAN_EQUALS","value":"1"}]}]}]}]